[
    {
        "Year": "2023",
        "Month": "Δεκέμβριος",
        "Category": "Ανάληψη",
        "Φυσικοχημικές Παράμετροι": "Θολότητα NTU",
        "Μονάδα μέτρησης": "NTU",
        "Τιμή": "0,089",
        "Παραμετρική τιμή1": "<1,0"
    },
    {
        "Year": "2023",
        "Month": "Δεκέμβριος",
        "Category": "Ανάληψη",
        "Φυσικοχημικές Παράμετροι": "Χρώμα",
        "Μονάδα μέτρησης": "mg/l Pt-Co",
        "Τιμή": "<5 ^3",
        "Παραμετρική τιμή1": "≤15"
    },
    {
        "Year": "2023",
        "Month": "Δεκέμβριος",
        "Category": "Ανάληψη",
        "Φυσικοχημικές Παράμετροι": "Αργίλιο",
        "Μονάδα μέτρησης": "μg Al/l",
        "Τιμή": "ΔΠ^5",
        "Παραμετρική τιμή1": "200"
    },
    {
        "Year": "2023",
        "Month": "Δεκέμβριος",
        "Category": "Ανάληψη",
        "Φυσικοχημικές Παράμετροι": "Χλωριούχα",
        "Μονάδα μέτρησης": "mg Cl⁻/ I⁻",
        "Τιμή": "20",
        "Παραμετρική τιμή1": "250"
    },
    {
        "Year": "2023",
        "Month": "Δεκέμβριος",
        "Category": "Ανάληψη",
        "Φυσικοχημικές Παράμετροι": "Αγωγιμότητα",
        "Μονάδα μέτρησης": "μS/cm στους 20°C",
        "Τιμή": "525",
        "Παραμετρική τιμή1": "2500"
    },
    {
        "Year": "2023",
        "Month": "Δεκέμβριος",
        "Category": "Ανάληψη",
        "Φυσικοχημικές Παράμετροι": "Συγκέντρωση ιόντων υδρογόνου",
        "Μονάδα μέτρησης": "μονάδες pH",
        "Τιμή": "7,5",
        "Παραμετρική τιμή1": "≥6,5 και ≤9,5"
    },
    {
        "Year": "2023",
        "Month": "Δεκέμβριος",
        "Category": "Ανάληψη",
        "Φυσικοχημικές Παράμετροι": "Υπολειμματικό χλώριο",
        "Μονάδα μέτρησης": "mg/l",
        "Τιμή": "0,38",
        "Παραμετρική τιμή1": "≥0,2^2"
    },
    {
        "Year": "2023",
        "Month": "Νοέμβριος",
        "Category": "Ανάληψη",
        "Φυσικοχημικές Παράμετροι": "Θολότητα NTU",
        "Μονάδα μέτρησης": "NTU",
        "Τιμή": "0,083",
        "Παραμετρική τιμή1": "<1,0"
    },
    {
        "Year": "2023",
        "Month": "Νοέμβριος",
        "Category": "Ανάληψη",
        "Φυσικοχημικές Παράμετροι": "Χρώμα",
        "Μονάδα μέτρησης": "mg/l Pt-Co",
        "Τιμή": "<5 ^3",
        "Παραμετρική τιμή1": "≤15"
    },
    {
        "Year": "2023",
        "Month": "Νοέμβριος",
        "Category": "Ανάληψη",
        "Φυσικοχημικές Παράμετροι": "Αργίλιο",
        "Μονάδα μέτρησης": "μg Al/l",
        "Τιμή": "ΔΠ^5",
        "Παραμετρική τιμή1": "200"
    },
    {
        "Year": "2023",
        "Month": "Νοέμβριος",
        "Category": "Ανάληψη",
        "Φυσικοχημικές Παράμετροι": "Χλωριούχα",
        "Μονάδα μέτρησης": "mg Cl⁻/ I⁻",
        "Τιμή": "25,2",
        "Παραμετρική τιμή1": "250"
    },
    {
        "Year": "2023",
        "Month": "Νοέμβριος",
        "Category": "Ανάληψη",
        "Φυσικοχημικές Παράμετροι": "Αγωγιμότητα",
        "Μονάδα μέτρησης": "μS/cm στους 20°C",
        "Τιμή": "534",
        "Παραμετρική τιμή1": "2500"
    },
    {
        "Year": "2023",
        "Month": "Νοέμβριος",
        "Category": "Ανάληψη",
        "Φυσικοχημικές Παράμετροι": "Συγκέντρωση ιόντων υδρογόνου",
        "Μονάδα μέτρησης": "μονάδες pH",
        "Τιμή": "7,4",
        "Παραμετρική τιμή1": "≥6,5 και ≤9,5"
    },
    {
        "Year": "2023",
        "Month": "Νοέμβριος",
        "Category": "Ανάληψη",
        "Φυσικοχημικές Παράμετροι": "Υπολειμματικό χλώριο",
        "Μονάδα μέτρησης": "mg/l",
        "Τιμή": "0,4",
        "Παραμετρική τιμή1": "≥0,2^2"
    },
    {
        "Year": "2023",
        "Month": "Οκτώβριος",
        "Category": "Ανάληψη",
        "Φυσικοχημικές Παράμετροι": "Θολότητα NTU",
        "Μονάδα μέτρησης": "NTU",
        "Τιμή": "<0,050^3",
        "Παραμετρική τιμή1": "<1,0"
    },
    {
        "Year": "2023",
        "Month": "Οκτώβριος",
        "Category": "Ανάληψη",
        "Φυσικοχημικές Παράμετροι": "Χρώμα",
        "Μονάδα μέτρησης": "mg/l Pt-Co",
        "Τιμή": "<5 ^3",
        "Παραμετρική τιμή1": "≤15"
    },
    {
        "Year": "2023",
        "Month": "Οκτώβριος",
        "Category": "Ανάληψη",
        "Φυσικοχημικές Παράμετροι": "Αργίλιο",
        "Μονάδα μέτρησης": "μg Al/l",
        "Τιμή": "ΔΠ^5",
        "Παραμετρική τιμή1": "200"
    },
    {
        "Year": "2023",
        "Month": "Οκτώβριος",
        "Category": "Ανάληψη",
        "Φυσικοχημικές Παράμετροι": "Χλωριούχα",
        "Μονάδα μέτρησης": "mg Cl⁻/ I⁻",
        "Τιμή": "27,2",
        "Παραμετρική τιμή1": "250"
    },
    {
        "Year": "2023",
        "Month": "Οκτώβριος",
        "Category": "Ανάληψη",
        "Φυσικοχημικές Παράμετροι": "Αγωγιμότητα",
        "Μονάδα μέτρησης": "μS/cm στους 20°C",
        "Τιμή": "545",
        "Παραμετρική τιμή1": "2500"
    },
    {
        "Year": "2023",
        "Month": "Οκτώβριος",
        "Category": "Ανάληψη",
        "Φυσικοχημικές Παράμετροι": "Συγκέντρωση ιόντων υδρογόνου",
        "Μονάδα μέτρησης": "μονάδες pH",
        "Τιμή": "7,3",
        "Παραμετρική τιμή1": "≥6,5 και ≤9,5"
    },
    {
        "Year": "2023",
        "Month": "Οκτώβριος",
        "Category": "Ανάληψη",
        "Φυσικοχημικές Παράμετροι": "Υπολειμματικό χλώριο",
        "Μονάδα μέτρησης": "mg/l",
        "Τιμή": "0,38",
        "Παραμετρική τιμή1": "≥0,2^2"
    },
    {
        "Year": "2023",
        "Month": "Σεπτέμβριος",
        "Category": "Ανάληψη",
        "Φυσικοχημικές Παράμετροι": "Θολότητα NTU",
        "Μονάδα μέτρησης": "NTU",
        "Τιμή": "<0,050^3",
        "Παραμετρική τιμή1": "<1,0"
    },
    {
        "Year": "2023",
        "Month": "Σεπτέμβριος",
        "Category": "Ανάληψη",
        "Φυσικοχημικές Παράμετροι": "Χρώμα",
        "Μονάδα μέτρησης": "mg/l Pt-Co",
        "Τιμή": "<5 ^3",
        "Παραμετρική τιμή1": "≤15"
    },
    {
        "Year": "2023",
        "Month": "Σεπτέμβριος",
        "Category": "Ανάληψη",
        "Φυσικοχημικές Παράμετροι": "Αργίλιο",
        "Μονάδα μέτρησης": "μg Al/l",
        "Τιμή": "ΔΠ^5",
        "Παραμετρική τιμή1": "200"
    },
    {
        "Year": "2023",
        "Month": "Σεπτέμβριος",
        "Category": "Ανάληψη",
        "Φυσικοχημικές Παράμετροι": "Χλωριούχα",
        "Μονάδα μέτρησης": "mg Cl⁻/ I⁻",
        "Τιμή": "22,0",
        "Παραμετρική τιμή1": "250"
    },
    {
        "Year": "2023",
        "Month": "Σεπτέμβριος",
        "Category": "Ανάληψη",
        "Φυσικοχημικές Παράμετροι": "Αγωγιμότητα",
        "Μονάδα μέτρησης": "μS/cm στους 20°C",
        "Τιμή": "531",
        "Παραμετρική τιμή1": "2500"
    },
    {
        "Year": "2023",
        "Month": "Σεπτέμβριος",
        "Category": "Ανάληψη",
        "Φυσικοχημικές Παράμετροι": "Συγκέντρωση ιόντων υδρογόνου",
        "Μονάδα μέτρησης": "μονάδες pH",
        "Τιμή": "7,4",
        "Παραμετρική τιμή1": "≥6,5 και ≤9,5"
    },
    {
        "Year": "2023",
        "Month": "Σεπτέμβριος",
        "Category": "Ανάληψη",
        "Φυσικοχημικές Παράμετροι": "Υπολειμματικό χλώριο",
        "Μονάδα μέτρησης": "mg/l",
        "Τιμή": "0,21",
        "Παραμετρική τιμή1": "≥0,2^2"
    },
    
    {
        "Year": "2024",
        "Month": "Απρίλιος",
        "Category": "Ανάληψη",
        "Φυσικοχημικές Παράμετροι": "Θολότητα NTU",
        "Μονάδα μέτρησης": "NTU",
        "Τιμή": "<0,050 ^3",
        "Παραμετρική τιμή1": "<1,0"
    },
    {
        "Year": "2024",
        "Month": "Απρίλιος",
        "Category": "Ανάληψη",
        "Φυσικοχημικές Παράμετροι": "Χρώμα",
        "Μονάδα μέτρησης": "mg/l Pt-Co",
        "Τιμή": "<5 ^3",
        "Παραμετρική τιμή1": "≤15"
    },
    {
        "Year": "2024",
        "Month": "Απρίλιος",
        "Category": "Ανάληψη",
        "Φυσικοχημικές Παράμετροι": "Αργίλιο",
        "Μονάδα μέτρησης": "μg Al/l",
        "Τιμή": "ΔΠ ^5",
        "Παραμετρική τιμή1": "200"
    },
    {
        "Year": "2024",
        "Month": "Απρίλιος",
        "Category": "Ανάληψη",
        "Φυσικοχημικές Παράμετροι": "Χλωριούχα",
        "Μονάδα μέτρησης": "mg Cl⁻/ I⁻",
        "Τιμή": "26,4",
        "Παραμετρική τιμή1": "250"
    },
    {
        "Year": "2024",
        "Month": "Απρίλιος",
        "Category": "Ανάληψη",
        "Φυσικοχημικές Παράμετροι": "Αγωγιμότητα",
        "Μονάδα μέτρησης": "μS/cm στους 20°C",
        "Τιμή": "550",
        "Παραμετρική τιμή1": "2500"
    },
    {
        "Year": "2024",
        "Month": "Απρίλιος",
        "Category": "Ανάληψη",
        "Φυσικοχημικές Παράμετροι": "Συγκέντρωση ιόντων υδρογόνου",
        "Μονάδα μέτρησης": "μονάδες pH",
        "Τιμή": "7,4",
        "Παραμετρική τιμή1": "≥6,5 και ≤9,5"
    },
    {
        "Year": "2024",
        "Month": "Απρίλιος",
        "Category": "Ανάληψη",
        "Φυσικοχημικές Παράμετροι": "Υπολειμματικό χλώριο",
        "Μονάδα μέτρησης": "mg/l",
        "Τιμή": "0,25",
        "Παραμετρική τιμή1": "≥0,2^2"
    },
    {
        "Year": "2024",
        "Month": "Μάρτιος",
        "Category": "Ανάληψη",
        "Φυσικοχημικές Παράμετροι": "Θολότητα NTU",
        "Μονάδα μέτρησης": "NTU",
        "Τιμή": "0,097",
        "Παραμετρική τιμή1": "<1,0"
    },
    {
        "Year": "2024",
        "Month": "Μάρτιος",
        "Category": "Ανάληψη",
        "Φυσικοχημικές Παράμετροι": "Χρώμα",
        "Μονάδα μέτρησης": "mg/l Pt-Co",
        "Τιμή": "<5 ^3",
        "Παραμετρική τιμή1": "≤15"
    },
    {
        "Year": "2024",
        "Month": "Μάρτιος",
        "Category": "Ανάληψη",
        "Φυσικοχημικές Παράμετροι": "Αργίλιο",
        "Μονάδα μέτρησης": "μg Al/l",
        "Τιμή": "ΔΠ ^5",
        "Παραμετρική τιμή1": "200"
    },
    {
        "Year": "2024",
        "Month": "Μάρτιος",
        "Category": "Ανάληψη",
        "Φυσικοχημικές Παράμετροι": "Χλωριούχα",
        "Μονάδα μέτρησης": "mg Cl⁻/ I⁻",
        "Τιμή": "8,4",
        "Παραμετρική τιμή1": "250"
    },
    {
        "Year": "2024",
        "Month": "Μάρτιος",
        "Category": "Ανάληψη",
        "Φυσικοχημικές Παράμετροι": "Αγωγιμότητα",
        "Μονάδα μέτρησης": "μS/cm στους 20°C",
        "Τιμή": "490",
        "Παραμετρική τιμή1": "2500"
    },
    {
        "Year": "2024",
        "Month": "Μάρτιος",
        "Category": "Ανάληψη",
        "Φυσικοχημικές Παράμετροι": "Συγκέντρωση ιόντων υδρογόνου",
        "Μονάδα μέτρησης": "μονάδες pH",
        "Τιμή": "7,5",
        "Παραμετρική τιμή1": "≥6,5 και ≤9,5"
    },
    {
        "Year": "2024",
        "Month": "Μάρτιος",
        "Category": "Ανάληψη",
        "Φυσικοχημικές Παράμετροι": "Υπολειμματικό χλώριο",
        "Μονάδα μέτρησης": "mg/l",
        "Τιμή": "0,36",
        "Παραμετρική τιμή1": "≥0,2^2"
    },
    {
        "Year": "2024",
        "Month": "Φεβρουάριος",
        "Category": "Ανάληψη",
        "Φυσικοχημικές Παράμετροι": "Θολότητα NTU",
        "Μονάδα μέτρησης": "NTU",
        "Τιμή": "0,109",
        "Παραμετρική τιμή1": "<1,0"
    },
    {
        "Year": "2024",
        "Month": "Φεβρουάριος",
        "Category": "Ανάληψη",
        "Φυσικοχημικές Παράμετροι": "Χρώμα",
        "Μονάδα μέτρησης": "mg/l Pt-Co",
        "Τιμή": "<5 ^3",
        "Παραμετρική τιμή1": "≤15"
    },
    {
        "Year": "2024",
        "Month": "Φεβρουάριος",
        "Category": "Ανάληψη",
        "Φυσικοχημικές Παράμετροι": "Αργίλιο",
        "Μονάδα μέτρησης": "μg Al/l",
        "Τιμή": "ΔΠ^5",
        "Παραμετρική τιμή1": "200"
    },
    {
        "Year": "2024",
        "Month": "Φεβρουάριος",
        "Category": "Ανάληψη",
        "Φυσικοχημικές Παράμετροι": "Χλωριούχα",
        "Μονάδα μέτρησης": "mg Cl⁻/ I⁻",
        "Τιμή": "29",
        "Παραμετρική τιμή1": "250"
    },
    {
        "Year": "2024",
        "Month": "Φεβρουάριος",
        "Category": "Ανάληψη",
        "Φυσικοχημικές Παράμετροι": "Αγωγιμότητα",
        "Μονάδα μέτρησης": "μS/cm στους 20°C",
        "Τιμή": "552",
        "Παραμετρική τιμή1": "2500"
    },
    {
        "Year": "2024",
        "Month": "Φεβρουάριος",
        "Category": "Ανάληψη",
        "Φυσικοχημικές Παράμετροι": "Συγκέντρωση ιόντων υδρογόνου",
        "Μονάδα μέτρησης": "μονάδες pH",
        "Τιμή": "7,5",
        "Παραμετρική τιμή1": "≥6,5 και ≤9,5"
    },
    {
        "Year": "2024",
        "Month": "Φεβρουάριος",
        "Category": "Ανάληψη",
        "Φυσικοχημικές Παράμετροι": "Υπολειμματικό χλώριο",
        "Μονάδα μέτρησης": "mg/l",
        "Τιμή": "0,34",
        "Παραμετρική τιμή1": "≥0,2^2"
    },
    {
        "Year": "2024",
        "Month": "Ιανουάριος",
        "Category": "Ανάληψη",
        "Φυσικοχημικές Παράμετροι": "Θολότητα NTU",
        "Μονάδα μέτρησης": "NTU",
        "Τιμή": "0,082",
        "Παραμετρική τιμή1": "<1,0"
    },
    {
        "Year": "2024",
        "Month": "Ιανουάριος",
        "Category": "Ανάληψη",
        "Φυσικοχημικές Παράμετροι": "Χρώμα",
        "Μονάδα μέτρησης": "mg/l Pt-Co",
        "Τιμή": "<5 ^3",
        "Παραμετρική τιμή1": "≤15"
    },
    {
        "Year": "2024",
        "Month": "Ιανουάριος",
        "Category": "Ανάληψη",
        "Φυσικοχημικές Παράμετροι": "Αργίλιο",
        "Μονάδα μέτρησης": "μg Al/l",
        "Τιμή": "ΔΠ^5",
        "Παραμετρική τιμή1": "200"
    },
    {
        "Year": "2024",
        "Month": "Ιανουάριος",
        "Category": "Ανάληψη",
        "Φυσικοχημικές Παράμετροι": "Χλωριούχα",
        "Μονάδα μέτρησης": "mg Cl⁻/ I⁻",
        "Τιμή": "ΔΠ^5",
        "Παραμετρική τιμή1": "250"
    },
    {
        "Year": "2024",
        "Month": "Ιανουάριος",
        "Category": "Ανάληψη",
        "Φυσικοχημικές Παράμετροι": "Αγωγιμότητα",
        "Μονάδα μέτρησης": "μS/cm στους 20°C",
        "Τιμή": "558",
        "Παραμετρική τιμή1": "2500"
    },
    {
        "Year": "2024",
        "Month": "Ιανουάριος",
        "Category": "Ανάληψη",
        "Φυσικοχημικές Παράμετροι": "Συγκέντρωση ιόντων υδρογόνου",
        "Μονάδα μέτρησης": "μονάδες pH",
        "Τιμή": "7,4",
        "Παραμετρική τιμή1": "≥6,5 και ≤9,5"
    },
    {
        "Year": "2024",
        "Month": "Ιανουάριος",
        "Category": "Ανάληψη",
        "Φυσικοχημικές Παράμετροι": "Υπολειμματικό χλώριο",
        "Μονάδα μέτρησης": "mg/l",
        "Τιμή": "0,38",
        "Παραμετρική τιμή1": "≥0,2^2"
    }

]